{"cameraMode":{"drawMode":0,"name":"Shaded","section":"Shading Mode"},"sceneLighting":true,"audioPlay":false,"sceneViewState":{"m_AlwaysRefresh":false,"showFog":true,"showSkybox":true,"showFlares":true,"showImageEffects":true,"showParticleSystems":true,"showVisualEffectGraphs":true,"m_FxEnabled":true},"in2DMode":false,"pivot":{"x":320.0,"y":240.0,"z":0.0},"rotation":{"x":0.06871073693037033,"y":0.08221044391393662,"z":-0.005681541282683611,"w":0.9942283034324646},"size":400.0,"orthographic":false}